configx/__init__.py
configx/core/__init__.py
configx/core/errors.py
configx/core/node.py
configx/core/tree.py
configx/qlang/__init__.py
configx/qlang/configxql.lark
configx/qlang/interpreter.py
configx/qlang/parser.py
configx/runtime/configx.py
configx/storage/__init__.py
configx/storage/runtime.py
configx/storage/snapshot.py
configx/storage/wal.py
pyconfigx-0.1.2.dist-info/licenses/LICENSE
pyconfigx-0.1.2.dist-info/METADATA
pyconfigx-0.1.2.dist-info/WHEEL
pyconfigx-0.1.2.dist-info/top_level.txt
pyconfigx-0.1.2.dist-info/RECORD
