Metadata-Version: 2.4
Name: pyconfigx
Version: 0.1.2
Summary: A hierarchical configuration and knowledge engine for dynamic systems
Author: Aditya Gaur
License: MIT License
Project-URL: Homepage, https://github.com/xdityagr/ConfigX
Project-URL: Repository, https://github.com/xdityagr/ConfigX
Classifier: Programming Language :: Python :: 3
Classifier: Operating System :: OS Independent
Requires-Python: >=3.9
License-File: LICENSE
Requires-Dist: lark
Requires-Dist: colorama
Dynamic: license-file
